stl2cad/__init__.py
stl2cad/cli.py
stl2cad/utilities.py
stl2cad-0.2.0.dist-info/METADATA
stl2cad-0.2.0.dist-info/WHEEL
stl2cad-0.2.0.dist-info/entry_points.txt
stl2cad-0.2.0.dist-info/top_level.txt
stl2cad-0.2.0.dist-info/RECORD
