Metadata-Version: 2.1
Name: stl2cad
Version: 0.2.0
Summary: Convert STL to CAD formats.
Project-URL: Homepage, https://github.com/kieran-mackle/stl2cad
Project-URL: Bug Tracker, https://github.com/kieran-mackle/stl2cad/issues
Requires-Python: >=3.11
Requires-Dist: click
Provides-Extra: dev
Requires-Dist: ruff>=0.7.4; extra == "dev"
Requires-Dist: commitizen>=3.31.0; extra == "dev"
Requires-Dist: pre-commit>=3.4.0; extra == "dev"
